setup.py
fishfinder/__init__.py
fishfinder/main.py
fishfinder.egg-info/PKG-INFO
fishfinder.egg-info/SOURCES.txt
fishfinder.egg-info/dependency_links.txt
fishfinder.egg-info/namespace_packages.txt
fishfinder.egg-info/not-zip-safe
fishfinder.egg-info/requires.txt
fishfinder.egg-info/top_level.txt