Metadata-Version: 1.1
Name: fishfinder
Version: 0.0.3
Summary: recursively search all possibilities until the optimal set is found
Home-page: http://github.com/abelsonlive/fishfinder
Author: Brian Abelson
Author-email: brianabelson@gmail.com
License: MIT
Platform: UNKNOWN
Classifier: Development Status :: 3 - Alpha
Classifier: Intended Audience :: Developers
Classifier: License :: OSI Approved :: MIT License
Classifier: Operating System :: OS Independent
Classifier: Programming Language :: Python
